lightgraph/__init__.py
lightgraph/network.py
lightgraph/assets/d3.v7.min.js
lightgraph/assets/lightgraph.js
lightgraph-0.2.0.dist-info/WHEEL
lightgraph-0.2.0.dist-info/METADATA
lightgraph-0.2.0.dist-info/RECORD
